parcllabs/__init__.py
parcllabs/__version__.py
parcllabs/common.py
parcllabs/enums.py
parcllabs/exceptions.py
parcllabs/parcllabs_client.py
parcllabs/schemas/__init__.py
parcllabs/schemas/schemas.py
parcllabs/services/__init__.py
parcllabs/services/data_utils.py
parcllabs/services/parcllabs_service.py
parcllabs/services/search.py
parcllabs/services/validators.py
parcllabs/services/metrics/portfolio_size_service.py
parcllabs/services/metrics/property_type_service.py
parcllabs/services/properties/property_address.py
parcllabs/services/properties/property_events_service.py
parcllabs/services/properties/property_search.py
parcllabs/services/properties/property_v2.py
parcllabs-1.16.2.dist-info/METADATA
parcllabs-1.16.2.dist-info/WHEEL
parcllabs-1.16.2.dist-info/licenses/LICENSE
parcllabs-1.16.2.dist-info/RECORD
