Metadata-Version: 2.4
Name: parcllabs
Version: 1.16.2
Summary: Python SDK for ParclLabs API
Project-URL: Homepage, https://github.com/ParclLabs/parcllabs-python
Author-email: ParclLabs <team@parcllabs.com>
License: MIT License
License-File: LICENSE
Keywords: analytics,api,parcllabs,real estate
Classifier: Development Status :: 3 - Alpha
Classifier: Intended Audience :: Developers
Classifier: Programming Language :: Python :: 3
Classifier: Programming Language :: Python :: 3.9
Classifier: Programming Language :: Python :: 3.10
Classifier: Programming Language :: Python :: 3.11
Classifier: Programming Language :: Python :: 3.12
Requires-Dist: numpy
Requires-Dist: pandas
Requires-Dist: pydantic>=2.0.0
Requires-Dist: requests
Provides-Extra: test
Requires-Dist: pytest; extra == 'test'
Requires-Dist: responses; extra == 'test'
